tilekiln/__init__.py
tilekiln/config.py
tilekiln/definition.py
tilekiln/errors.py
tilekiln/generator.py
tilekiln/kiln.py
tilekiln/main.py
tilekiln/metric.py
tilekiln/prometheus.py
tilekiln/storage.py
tilekiln/tile.py
tilekiln/tilerange.py
tilekiln/tileset.py
tilekiln/dev/__init__.py
tilekiln/scripts/__init__.py
tilekiln/scripts/config.py
tilekiln/scripts/generate.py
tilekiln/scripts/serve.py
tilekiln/scripts/storage.py
tilekiln/server/__init__.py
tilekiln-0.8.1.dist-info/METADATA
tilekiln-0.8.1.dist-info/WHEEL
tilekiln-0.8.1.dist-info/entry_points.txt
tilekiln-0.8.1.dist-info/licenses/LICENSE
tilekiln-0.8.1.dist-info/RECORD
