Metadata-Version: 2.4
Name: tilekiln
Version: 0.8.1
Summary: A set of command-line utilities to generate and serve Mapbox Vector Tiles (MVTs)
Project-URL: Bug Reports, https://github.com/pnorman/tilekiln/issues
Project-URL: Homepage, https://github.com/pnorman/tilekiln
Project-URL: Source, https://github.com/pnorman/tilekiln/
Author-email: Paul Norman <osm@paulnorman.ca>
License-Expression: GPL-3.0-or-later
License-File: LICENSE
Keywords: mvt,openstreetmap,osm
Classifier: Development Status :: 4 - Beta
Classifier: Environment :: Console
Classifier: License :: OSI Approved :: GNU General Public License v3 or later (GPLv3+)
Classifier: Operating System :: OS Independent
Classifier: Programming Language :: Python :: 3
Classifier: Topic :: Scientific/Engineering :: GIS
Requires-Python: <4,>=3.10
Requires-Dist: click
Requires-Dist: fastapi
Requires-Dist: fs
Requires-Dist: jinja2
Requires-Dist: pmtiles
Requires-Dist: prometheus-client
Requires-Dist: psycopg
Requires-Dist: psycopg-pool
Requires-Dist: pyyaml
Requires-Dist: tqdm
Requires-Dist: uvicorn
Provides-Extra: test
Requires-Dist: pytest; extra == 'test'
